htag/__init__.py
htag/__main__.py
htag/attrs.py
htag/render.py
htag/tag.py
htag/ui.py
htag/runners/__init__.py
htag/runners/chromeappmode.py
htag/runners/pyscript.py
htag/runners/pywebview.py
htag/runners/runner.py
htag/runners/commons/__init__.py
htag/runners/server/__init__.py
htag-0.202.0.dist-info/METADATA
htag-0.202.0.dist-info/WHEEL
htag-0.202.0.dist-info/entry_points.txt
htag-0.202.0.dist-info/licenses/LICENSE
htag-0.202.0.dist-info/RECORD
