Metadata-Version: 2.4
Name: htag
Version: 0.202.0
Summary: GUI toolkit for building GUI toolkits (and create beautiful applications for mobile, web, and desktop from a single python3 codebase)
Project-URL: Homepage, https://github.com/manatlan/htag
Project-URL: Repository, https://github.com/manatlan/htag
Project-URL: Documentation, https://manatlan.github.io/htag/
Author-email: manatlan <manatlan@gmail.com>
License: MIT
License-File: LICENSE
Keywords: android,apk,asyncio,cef,desktop,electron,gui,html,http,kivy,mobile,pyscript,pywebview,starlette,tornado,uvicorn,web,websocket
Classifier: License :: OSI Approved :: Apache Software License
Classifier: Operating System :: OS Independent
Classifier: Topic :: Software Development :: Build Tools
Classifier: Topic :: Software Development :: Libraries :: Python Modules
Requires-Python: >=3.7
Provides-Extra: dev
Requires-Dist: fake-winreg>=1.6; extra == 'dev'
Requires-Dist: pytest-asyncio>=0.19; extra == 'dev'
Requires-Dist: pytest-cov>=3; extra == 'dev'
Requires-Dist: pytest>=6; extra == 'dev'
Requires-Dist: pywebview>=3.6; extra == 'dev'
Requires-Dist: selenium>=4; extra == 'dev'
